oomol_connect_sdk/__init__.py
oomol_connect_sdk/applets.py
oomol_connect_sdk/blocks.py
oomol_connect_sdk/client.py
oomol_connect_sdk/errors.py
oomol_connect_sdk/packages.py
oomol_connect_sdk/tasks.py
oomol_connect_sdk/types.py
oomol_connect_sdk/utils.py
oomol_connect_sdk-1.0.3.dist-info/licenses/LICENSE
oomol_connect_sdk-1.0.3.dist-info/METADATA
oomol_connect_sdk-1.0.3.dist-info/WHEEL
oomol_connect_sdk-1.0.3.dist-info/top_level.txt
oomol_connect_sdk-1.0.3.dist-info/RECORD
