Metadata-Version: 2.4
Name: oomol-connect-sdk
Version: 1.0.3
Summary: Oomol Connect SDK for Python
Author-email: Oomol Team <team@oomol.com>
License: MIT
Project-URL: Homepage, https://github.com/oomol/oomol-connect-sdk-py
Project-URL: Documentation, https://github.com/oomol/oomol-connect-sdk-py#readme
Project-URL: Repository, https://github.com/oomol/oomol-connect-sdk-py.git
Project-URL: Issues, https://github.com/oomol/oomol-connect-sdk-py/issues
Keywords: oomol,connect,sdk,api
Classifier: Development Status :: 4 - Beta
Classifier: Intended Audience :: Developers
Classifier: License :: OSI Approved :: MIT License
Classifier: Programming Language :: Python :: 3
Classifier: Programming Language :: Python :: 3.8
Classifier: Programming Language :: Python :: 3.9
Classifier: Programming Language :: Python :: 3.10
Classifier: Programming Language :: Python :: 3.11
Classifier: Programming Language :: Python :: 3.12
Classifier: Typing :: Typed
Requires-Python: >=3.8
License-File: LICENSE
Requires-Dist: httpx>=0.27.0
Provides-Extra: dev
Requires-Dist: pytest>=7.0.0; extra == "dev"
Requires-Dist: pytest-asyncio>=0.21.0; extra == "dev"
Requires-Dist: mypy>=1.0.0; extra == "dev"
Requires-Dist: black>=23.0.0; extra == "dev"
Requires-Dist: isort>=5.12.0; extra == "dev"
Requires-Dist: flake8>=6.0.0; extra == "dev"
Dynamic: license-file
